avaris/__init__.py
avaris/__main__.py
avaris/api/__init__.py
avaris/api/models.py
avaris/api/output.py
avaris/cli.py
avaris/config/__init__.py
avaris/config/config_loader.py
avaris/config/config_manager.py
avaris/config/error.py
avaris/config/exception.py
avaris/config/value_parser.py
avaris/data/__init__.py
avaris/data/datamanager.py
avaris/data/models.py
avaris/data/s3.py
avaris/data/shipper.py
avaris/data/sql.py
avaris/defaults.py
avaris/engine/__init__.py
avaris/engine/commands.py
avaris/engine/engine.py
avaris/engine/listener.py
avaris/engine/start.py
avaris/executor/__init__.py
avaris/executor/apicall.py
avaris/executor/endpoint.py
avaris/executor/executor.py
avaris/executor/fetch_file.py
avaris/executor/github_release.py
avaris/executor/http_get.py
avaris/executor/shell.py
avaris/handler/__init__.py
avaris/handler/handler.py
avaris/manage.py
avaris/registry.py
avaris/service/__init__.py
avaris/service/dataqueue.py
avaris/service/datasource.py
avaris/service/service.py
avaris/task/__init__.py
avaris/task/plugins.py
avaris/task/task_registry.py
avaris/task/taskmaster.py
avaris/task/taskmaster_apscheduler.py
avaris/task/taskmaster_celery.py
avaris/utils/__init__.py
avaris/utils/auth.py
avaris/utils/logging.py
avaris/utils/management.py
avaris/utils/parse.py
avaris-0.2.3.dist-info/LICENSE
avaris-0.2.3.dist-info/METADATA
avaris-0.2.3.dist-info/WHEEL
avaris-0.2.3.dist-info/entry_points.txt
avaris-0.2.3.dist-info/RECORD
