Metadata-Version: 2.1
Name: avaris
Version: 0.2.3
Summary: Task execution engine for data management and monitoring
License: Apache-2.0
Author: dennis
Author-email: denngohis@gmail.com
Requires-Python: >=3.10,<4.0
Classifier: License :: OSI Approved :: Apache Software License
Classifier: Programming Language :: Python :: 3
Classifier: Programming Language :: Python :: 3.10
Classifier: Programming Language :: Python :: 3.11
Classifier: Programming Language :: Python :: 3.12
Requires-Dist: aiofiles (>=23.2.1,<24.0.0)
Requires-Dist: aiohttp (>=3.9.3,<4.0.0)
Requires-Dist: aiosqlite (>=0.20.0,<0.21.0)
Requires-Dist: apscheduler (>=3.10.4,<4.0.0)
Requires-Dist: beautifulsoup4 (>=4.12.3,<5.0.0)
Requires-Dist: celery (>=5.3.6,<6.0.0)
Requires-Dist: click (>=8.1.7,<9.0.0)
Requires-Dist: colorlog (>=6.8.2,<7.0.0)
Requires-Dist: croniter (>=2.0.2,<3.0.0)
Requires-Dist: databases (>=0.9.0,<0.10.0)
Requires-Dist: fastapi (>=0.110.0,<0.111.0)
Requires-Dist: flask (>=3.0.2,<4.0.0)
Requires-Dist: httpx (>=0.27.0,<0.28.0)
Requires-Dist: pydantic (>=2.6.3,<3.0.0)
Requires-Dist: python-dotenv[cli] (>=1.0.1,<2.0.0)
Requires-Dist: pytz (>=2024.1,<2025.0)
Requires-Dist: pyyaml (>=6.0.1,<7.0.0)
Requires-Dist: requests (>=2.31.0,<3.0.0)
Requires-Dist: sqlalchemy (>=2.0.28,<3.0.0)
Requires-Dist: uvicorn (>=0.27.1,<0.28.0)
